qts2d/__init__.py
qts2d/base_transformer.py
qts2d/encoding/__init__.py
qts2d/encoding/qgaf.py
qts2d/encoding/qmtf.py
qts2d/encoding/qrp.py
qts2d/encoding/qsg.py
qts2d/encoding/tests/__init__.py
qts2d/encoding/tests/test_qgaf.py
qts2d/encoding/tests/test_qmtf.py
qts2d/encoding/tests/test_qrp.py
qts2d/encoding/tests/test_qsg.py
qts2d/tests/__init__.py
qts2d/tests/test_base_transformer.py
qts2d/utils/__init__.py
qts2d/utils/preprocessing.py
qts2d-0.1.0.dist-info/METADATA
qts2d-0.1.0.dist-info/WHEEL
qts2d-0.1.0.dist-info/licenses/LICENSE.txt
qts2d-0.1.0.dist-info/RECORD
