Metadata-Version: 2.4
Name: qts2d
Version: 0.1.0
Summary: Quantum-Based Image Encoding of Time Series
Project-URL: Homepage, https://github.com/sokolmarek/qts2d
Project-URL: Repository, https://github.com/sokolmarek/qts2d
Author-email: Marek Sokol <marek.sokol@cvut.cz>
License: Copyright (c) 2025, Marek Sokol and qts2d contributors
License-File: LICENSE.txt
Classifier: Intended Audience :: Science/Research
Classifier: License :: OSI Approved :: BSD License
Classifier: Operating System :: OS Independent
Classifier: Programming Language :: Python :: 3 :: Only
Classifier: Programming Language :: Python :: 3.10
Classifier: Programming Language :: Python :: 3.11
Classifier: Programming Language :: Python :: 3.12
Classifier: Programming Language :: Python :: 3.13
Classifier: Topic :: Scientific/Engineering
Classifier: Topic :: Software Development :: Libraries :: Python Modules
Requires-Python: >=3.10
Requires-Dist: numpy>=2.2.5
Requires-Dist: pyts>=0.13.0
Requires-Dist: qiskit-aer==0.17.0
Requires-Dist: qiskit-machine-learning==0.8.2
Requires-Dist: qiskit==1.4.2
Requires-Dist: scikit-learn>=1.6.1
